prts/__init__.py
prts/base/__init__.py
prts/base/time_series_metrics.py
prts/time_series_metrics/__init__.py
prts/time_series_metrics/fscore.py
prts/time_series_metrics/precision.py
prts/time_series_metrics/precision_recall.py
prts/time_series_metrics/recall.py
prts-1.0.0.3.dist-info/LICENSE
prts-1.0.0.3.dist-info/WHEEL
prts-1.0.0.3.dist-info/METADATA
prts-1.0.0.3.dist-info/RECORD
