Metadata-Version: 2.1
Name: prts
Version: 1.0.0.3
Summary: 
License: LICENSE
Author: Ryohei Izawa
Author-email: rizawa@ridge-i.com
Requires-Python: >=3.6,<4.0
Classifier: License :: Other/Proprietary License
Classifier: Programming Language :: Python :: 3
Classifier: Programming Language :: Python :: 3.6
Classifier: Programming Language :: Python :: 3.7
Classifier: Programming Language :: Python :: 3.8
Classifier: Programming Language :: Python :: 3.9
Requires-Dist: numpy (>=1.19.4,<2.0.0)
